Workbook

Sheet Sommaire
A1: Banque de QCM — Informatique
A2: 13 domaines · 585 questions · 3 niveaux de difficulté · réponses justifiées. Cliquez sur un domaine pour ouvrir sa feuille.
A4: Domaine | B4: Total | C4: Facile | D4: Moyen | E4: Difficile | F4: Feuille
A5: Algorithmique | B5: =COUNTA(Algorithmique!$B$4:$B$48) -> 45 | C5: =COUNTIF(Algorithmique!$B$4:$B$48,"Facile") -> 15 | D5: =COUNTIF(Algorithmique!$B$4:$B$48,"Moyen") -> 15 | E5: =COUNTIF(Algorithmique!$B$4:$B$48,"Difficile") -> 15 | F5: Ouvrir →
A6: Architecture des ordinateurs | B6: =COUNTA(Architecture!$B$4:$B$48) -> 45 | C6: =COUNTIF(Architecture!$B$4:$B$48,"Facile") -> 15 | D6: =COUNTIF(Architecture!$B$4:$B$48,"Moyen") -> 15 | E6: =COUNTIF(Architecture!$B$4:$B$48,"Difficile") -> 15 | F6: Ouvrir →
A7: Réseaux | B7: =COUNTA(Réseaux!$B$4:$B$48) -> 45 | C7: =COUNTIF(Réseaux!$B$4:$B$48,"Facile") -> 15 | D7: =COUNTIF(Réseaux!$B$4:$B$48,"Moyen") -> 15 | E7: =COUNTIF(Réseaux!$B$4:$B$48,"Difficile") -> 15 | F7: Ouvrir →
A8: Bases de données | B8: =COUNTA('Bases de données'!$B$4:$B$48) -> 45 | C8: =COUNTIF('Bases de données'!$B$4:$B$48,"Facile") -> 15 | D8: =COUNTIF('Bases de données'!$B$4:$B$48,"Moyen") -> 15 | E8: =COUNTIF('Bases de données'!$B$4:$B$48,"Difficile") -> 15 | F8: Ouvrir →
A9: SQL | B9: =COUNTA(SQL!$B$4:$B$48) -> 45 | C9: =COUNTIF(SQL!$B$4:$B$48,"Facile") -> 15 | D9: =COUNTIF(SQL!$B$4:$B$48,"Moyen") -> 15 | E9: =COUNTIF(SQL!$B$4:$B$48,"Difficile") -> 15 | F9: Ouvrir →
A10: Systèmes d'exploitation | B10: =COUNTA('Systèmes exploitation'!$B$4:$B$48) -> 45 | C10: =COUNTIF('Systèmes exploitation'!$B$4:$B$48,"Facile") -> 15 | D10: =COUNTIF('Systèmes exploitation'!$B$4:$B$48,"Moyen") -> 15 | E10: =COUNTIF('Systèmes exploitation'!$B$4:$B$48,"Difficile") -> 15 | F10: Ouvrir →
A11: Numération | B11: =COUNTA(Numération!$B$4:$B$48) -> 45 | C11: =COUNTIF(Numération!$B$4:$B$48,"Facile") -> 15 | D11: =COUNTIF(Numération!$B$4:$B$48,"Moyen") -> 15 | E11: =COUNTIF(Numération!$B$4:$B$48,"Difficile") -> 15 | F11: Ouvrir →
A12: PHP | B12: =COUNTA(PHP!$B$4:$B$48) -> 45 | C12: =COUNTIF(PHP!$B$4:$B$48,"Facile") -> 15 | D12: =COUNTIF(PHP!$B$4:$B$48,"Moyen") -> 15 | E12: =COUNTIF(PHP!$B$4:$B$48,"Difficile") -> 15 | F12: Ouvrir →
A13: POO — concepts généraux | B13: =COUNTA('POO concepts'!$B$4:$B$48) -> 45 | C13: =COUNTIF('POO concepts'!$B$4:$B$48,"Facile") -> 15 | D13: =COUNTIF('POO concepts'!$B$4:$B$48,"Moyen") -> 15 | E13: =COUNTIF('POO concepts'!$B$4:$B$48,"Difficile") -> 15 | F13: Ouvrir →
A14: C++ | B14: =COUNTA('C++'!$B$4:$B$48) -> 45 | C14: =COUNTIF('C++'!$B$4:$B$48,"Facile") -> 15 | D14: =COUNTIF('C++'!$B$4:$B$48,"Moyen") -> 15 | E14: =COUNTIF('C++'!$B$4:$B$48,"Difficile") -> 15 | F14: Ouvrir →
A15: POO Java | B15: =COUNTA('POO Java'!$B$4:$B$48) -> 45 | C15: =COUNTIF('POO Java'!$B$4:$B$48,"Facile") -> 15 | D15: =COUNTIF('POO Java'!$B$4:$B$48,"Moyen") -> 15 | E15: =COUNTIF('POO Java'!$B$4:$B$48,"Difficile") -> 15 | F15: Ouvrir →
A16: UML | B16: =COUNTA(UML!$B$4:$B$48) -> 45 | C16: =COUNTIF(UML!$B$4:$B$48,"Facile") -> 15 | D16: =COUNTIF(UML!$B$4:$B$48,"Moyen") -> 15 | E16: =COUNTIF(UML!$B$4:$B$48,"Difficile") -> 15 | F16: Ouvrir →
A17: Développement web | B17: =COUNTA('Développement web'!$B$4:$B$48) -> 45 | C17: =COUNTIF('Développement web'!$B$4:$B$48,"Facile") -> 15 | D17: =COUNTIF('Développement web'!$B$4:$B$48,"Moyen") -> 15 | E17: =COUNTIF('Développement web'!$B$4:$B$48,"Difficile") -> 15 | F17: Ouvrir →
A18: TOTAL | B18: =SUM(B5:B17) -> 585 | C18: =SUM(C5:C17) -> 195 | D18: =SUM(D5:D17) -> 195 | E18: =SUM(E5:E17) -> 195

Sheet Algorithmique
A1: QCM — Algorithmique
A2: 45 questions · 15 faciles · 15 moyennes · 15 difficiles — la bonne réponse est indiquée avec une explication.
A3: N° | B3: Difficulté | C3: Question | D3: Choix A | E3: Choix B | F3: Choix C | G3: Choix D | H3: Bonne réponse | I3: Explication
A4: 1 | B4: Facile | C4: Quelle structure de contrôle permet de répéter un bloc d'instructions tant qu'une condition est vraie ? | D4: La boucle tant que (while) | E4: La condition si (if) | F4: L'affectation | G4: La déclaration de variable | H4: A | I4: La boucle « tant que » (while) répète son bloc tant que la condition testée reste vraie ; elle s'arrête dès que la condition devient fausse.
A5: 2 | B5: Facile | C5: Dans une instruction conditionnelle si-sinon (if-else), le bloc « sinon » est exécuté quand : | D5: La condition est vraie | E5: La condition est fausse | F5: La condition est toujours exécutée | G5: Il y a une erreur | H5: B | I5: Le bloc « sinon » n'est exécuté que lorsque la condition du « si » est évaluée à faux.
A6: 3 | B6: Facile | C6: Combien de fois s'exécute le corps d'une boucle « pour i de 1 à 5 » (bornes incluses) ? | D6: 4 fois | E6: 6 fois | F6: 5 fois | G6: 1 fois | H6: C | I6: La boucle parcourt les valeurs 1, 2, 3, 4, 5, soit 5 itérations lorsque les deux bornes sont incluses.
A7: 4 | B7: Facile | C7: Qu'est-ce qu'une fonction récursive ? | D7: Une fonction qui ne renvoie rien | E7: Une fonction exécutée en parallèle | F7: Une fonction sans paramètre | G7: Une fonction qui s'appelle elle-même | H7: D | I7: Une fonction récursive est une fonction qui, dans sa définition, s'appelle elle-même pour résoudre un sous-problème.
A8: 5 | B8: Facile | C8: Quelle structure de données suit le principe LIFO (dernier entré, premier sorti) ? | D8: La pile (stack) | E8: La liste chaînée | F8: La file (queue) | G8: Le tableau | H8: A | I8: La pile fonctionne en LIFO : le dernier élément empilé est le premier à être dépilé.
A9: 6 | B9: Facile | C9: Quelle structure de données suit le principe FIFO (premier entré, premier sorti) ? | D9: La pile (stack) | E9: La file (queue) | F9: L'arbre binaire | G9: Le dictionnaire | H9: B | I9: La file fonctionne en FIFO : le premier élément inséré est le premier à être retiré.
A10: 7 | B10: Facile | C10: La recherche séquentielle (linéaire) dans un tableau consiste à : | D10: Diviser le tableau en deux à chaque étape | E10: Trier puis chercher | F10: Parcourir les éléments un par un jusqu'à trouver la valeur | G10: Utiliser une table de hachage | H10: C | I10: La recherche séquentielle examine chaque élément dans l'ordre jusqu'à trouver la valeur cherchée ou atteindre la fin.
A11: 8 | B11: Facile | C11: Que fait un algorithme de tri ? | D11: Il supprime les doublons | E11: Il inverse toujours le tableau | F11: Il compte les éléments | G11: Il ordonne les éléments selon un critère | H11: D | I11: Un algorithme de tri réorganise les éléments d'une collection selon un ordre défini (croissant ou décroissant).
A12: 9 | B12: Facile | C12: Quelle notation exprime la complexité asymptotique dans le pire des cas ? | D12: La notation Big-O (O) | E12: Le symbole Σ | F12: La lettre π | G12: Le symbole ∞ | H12: A | I12: La notation Big-O (grand O) décrit une borne supérieure de la complexité, typiquement le comportement dans le pire des cas.
A13: 10 | B13: Facile | C13: Une complexité en O(1) signifie que le temps d'exécution : | D13: Croît linéairement avec la taille des données | E13: Est constant, indépendant de la taille des données | F13: Croît de façon quadratique | G13: Double à chaque étape | H13: B | I13: O(1) désigne un temps constant : il ne dépend pas de la taille de l'entrée.
A14: 11 | B14: Facile | C14: Dans une boucle « pour », quel élément indique de combien varie le compteur à chaque tour ? | D14: La condition initiale | E14: Le corps de boucle | F14: Le pas (incrément) | G14: Le nom de la fonction | H14: C | I14: Le pas (ou incrément) définit la variation du compteur à chaque itération, souvent +1 par défaut.
A15: 12 | B15: Facile | C15: Qu'est-ce qu'un cas de base dans une fonction récursive ? | D15: Le cas qui provoque une erreur | E15: Le cas le plus fréquent | F15: Le premier appel de la fonction | G15: Le cas qui arrête la récursion sans nouvel appel | H15: D | I15: Le cas de base est la condition d'arrêt qui renvoie un résultat directement, sans relancer d'appel récursif ; il évite la récursion infinie.
... A48: 45 | B48: Difficile | C48: Pour inverser l'ordre des éléments d'une file en utilisant uniquement une structure auxiliaire, laquelle est la plus adaptée ? | D48: Une pile | E48: Une autre file | F48: Un dictionnaire | G48: Un arbre | H48: A | I48: En dépilant tous les éléments de la file dans une pile puis en les ressortant, on obtient l'ordre inversé grâce au comportement LIFO de la pile.

Sheet Architecture
A1: QCM — Architecture des ordinateurs
A2: 45 questions · 15 faciles · 15 moyennes · 15 difficiles — la bonne réponse est indiquée avec une explication.
A3: N° | B3: Difficulté | C3: Question | D3: Choix A | E3: Choix B | F3: Choix C | G3: Choix D | H3: Bonne réponse | I3: Explication
A4: 1 | B4: Facile | C4: Que signifie l'acronyme CPU ? | D4: Central Processing Unit | E4: Computer Power Unit | F4: Central Program Utility | G4: Control Peripheral Unit | H4: A | I4: CPU signifie Central Processing Unit, c'est-à-dire l'unité centrale de traitement, le processeur.
A5: 2 | B5: Facile | C5: Quel composant exécute les instructions d'un programme ? | D5: La mémoire RAM | E5: Le processeur (CPU) | F5: Le disque dur | G5: L'écran | H5: B | I5: Le processeur (CPU) est le composant qui interprète et exécute les instructions des programmes.
A6: 3 | B6: Facile | C6: Qu'est-ce qu'un registre dans un processeur ? | D6: Un périphérique de stockage externe | E6: Un bus de données | F6: Une petite mémoire très rapide interne au CPU | G6: Un port USB | H6: C | I6: Un registre est une mémoire de très petite taille et très rapide, située à l'intérieur du processeur, servant à stocker des données de travail.
A7: 4 | B7: Facile | C7: La mémoire vive d'un ordinateur est aussi appelée : | D7: ROM | E7: GPU | F7: CPU | G7: RAM | H7: D | I7: La mémoire vive porte le nom de RAM (Random Access Memory) ; elle est volatile et perd son contenu à l'extinction.
A8: 5 | B8: Facile | C8: Quelle caractéristique distingue la mémoire ROM de la RAM ? | D8: La ROM conserve ses données sans alimentation électrique | E8: La ROM est volatile | F8: La ROM est toujours plus grande que la RAM | G8: La ROM ne peut jamais être lue | H8: A | I8: La ROM (Read-Only Memory) est non volatile : elle conserve son contenu même sans alimentation, contrairement à la RAM.
A9: 6 | B9: Facile | C9: À quoi sert la mémoire cache dans un ordinateur ? | D9: À stocker définitivement les fichiers | E9: À accélérer l'accès aux données fréquemment utilisées par le CPU | F9: À afficher les images | G9: À alimenter la carte mère | H9: B | I9: Le cache est une mémoire rapide intermédiaire qui garde les données et instructions souvent utilisées, réduisant les temps d'accès du CPU à la RAM.
A10: 7 | B10: Facile | C10: Qu'est-ce qu'un bus dans un ordinateur ? | D10: Un logiciel | E10: Un type de processeur | F10: Un ensemble de lignes transportant des données entre composants | G10: Une mémoire non volatile | H10: C | I10: Un bus est un ensemble de conducteurs (lignes) qui transporte des informations (données, adresses, signaux de contrôle) entre les composants.
A11: 8 | B11: Facile | C11: Quelle porte logique renvoie 1 uniquement si ses deux entrées valent 1 ? | D11: OU (OR) | E11: OU EXCLUSIF (XOR) | F11: NON (NOT) | G11: ET (AND) | H11: D | I11: La porte ET (AND) ne produit 1 en sortie que lorsque toutes ses entrées valent 1.
A12: 9 | B12: Facile | C12: Que fait une porte logique NON (NOT) ? | D12: Elle inverse l'état de son entrée | E12: Elle additionne les entrées | F12: Elle compare deux entrées | G12: Elle stocke un bit | H12: A | I12: La porte NON (inverseur) produit la valeur opposée à son entrée : 0 devient 1 et 1 devient 0.
A13: 10 | B13: Facile | C13: Dans la hiérarchie mémoire, quel élément est le plus rapide mais le plus petit ? | D13: Le disque dur | E13: Les registres du CPU | F13: La RAM | G13: Le SSD | H13: B | I13: Les registres, internes au processeur, sont les mémoires les plus rapides mais de très faible capacité, au sommet de la hiérarchie.
A14: 11 | B14: Facile | C14: Que signifie l'acronyme RISC ? | D14: Rapid Integrated Storage Circuit | E14: Random Internal System Control | F14: Reduced Instruction Set Computer | G14: Read Instruction Simple Code | H14: C | I14: RISC signifie Reduced Instruction Set Computer : une architecture au jeu d'instructions réduit et simple.
A15: 12 | B15: Facile | C15: Quelle porte logique renvoie 1 si au moins une de ses entrées vaut 1 ? | D15: ET (AND) | E15: NAND | F15: NON (NOT) | G15: OU (OR) | H15: D | I15: La porte OU (OR) produit 1 dès qu'au moins une entrée vaut 1, et 0 seulement si toutes les entrées valent 0.
... A48: 45 | B48: Difficile | C48: Dans le mécanisme d'interruption, à quoi sert la sauvegarde du contexte (registres et compteur ordinal) ? | D48: À permettre de reprendre l'exécution du programme interrompu exactement où il en était | E48: À supprimer le programme en cours | F48: À accélérer l'horloge du processeur | G48: À vider la mémoire cache | H48: A | I48: Lors d'une interruption, le processeur sauvegarde le contexte (compteur ordinal, registres, état) afin de pouvoir, après traitement, restaurer cet état et reprendre le programme interrompu à l'endroit exact où il avait été suspendu.

Sheet Réseaux
A1: QCM — Réseaux
A2: 45 questions · 15 faciles · 15 moyennes · 15 difficiles — la bonne réponse est indiquée avec une explication.
A3: N° | B3: Difficulté | C3: Question | D3: Choix A | E3: Choix B | F3: Choix C | G3: Choix D | H3: Bonne réponse | I3: Explication
A4: 1 | B4: Facile | C4: Combien de couches comporte le modèle OSI ? | D4: 7 | E4: 4 | F4: 5 | G4: 8 | H4: A | I4: Le modèle OSI est composé de 7 couches : physique, liaison, réseau, transport, session, présentation et application.
A5: 2 | B5: Facile | C5: Quelle couche du modèle OSI est responsable du routage des paquets ? | D5: La couche transport | E5: La couche réseau | F5: La couche liaison de données | G5: La couche physique | H5: B | I5: La couche réseau (couche 3) gère l'adressage logique et le routage des paquets entre réseaux.
A6: 3 | B6: Facile | C6: Quel protocole est orienté connexion et garantit la livraison fiable des données ? | D6: UDP | E6: IP | F6: TCP | G6: ICMP | H6: C | I6: TCP est orienté connexion et assure une livraison fiable grâce aux accusés de réception et à la retransmission.
A7: 4 | B7: Facile | C7: Quelle est la longueur d'une adresse IPv4 ? | D7: 64 bits | E7: 128 bits | F7: 48 bits | G7: 32 bits | H7: D | I7: Une adresse IPv4 est codée sur 32 bits, généralement notée en quatre octets décimaux séparés par des points.
A8: 5 | B8: Facile | C8: Quel protocole traduit un nom de domaine en adresse IP ? | D8: DNS | E8: DHCP | F8: FTP | G8: SMTP | H8: A | I8: Le DNS (Domain Name System) résout les noms de domaine en adresses IP correspondantes.
A9: 6 | B9: Facile | C9: Quel protocole attribue automatiquement des adresses IP aux hôtes d'un réseau ? | D9: DNS | E9: DHCP | F9: ARP | G9: NAT | H9: B | I9: Le DHCP (Dynamic Host Configuration Protocol) attribue dynamiquement des adresses IP et d'autres paramètres réseau.
A10: 7 | B10: Facile | C10: Quel port est utilisé par défaut par le protocole HTTP ? | D10: 21 | E10: 25 | F10: 80 | G10: 443 | H10: C | I10: Le port 80 est le port par défaut du protocole HTTP ; HTTPS utilise le port 443.
A11: 8 | B11: Facile | C11: Quel équipement réseau interconnecte plusieurs réseaux différents et choisit les chemins ? | D11: Le commutateur (switch) | E11: Le concentrateur (hub) | F11: Le répéteur | G11: Le routeur | H11: D | I11: Le routeur interconnecte des réseaux distincts et détermine le meilleur chemin pour acheminer les paquets.
A12: 9 | B12: Facile | C12: Dans quelle topologie tous les équipements sont-ils reliés à un point central ? | D12: En étoile | E12: En bus | F12: En anneau | G12: En maille | H12: A | I12: Dans la topologie en étoile, chaque équipement est relié à un nœud central comme un commutateur.
A13: 10 | B13: Facile | C13: Quel protocole de transport est utilisé lorsqu'on privilégie la rapidité sans garantie de livraison ? | D13: TCP | E13: UDP | F13: HTTP | G13: FTP | H13: B | I13: UDP est un protocole sans connexion, rapide mais sans garantie de livraison ni de séquencement.
A14: 11 | B14: Facile | C14: Que signifie l'acronyme LAN ? | D14: Large Area Network | E14: Logical Access Node | F14: Local Area Network | G14: Link Aggregation Network | H14: C | I14: LAN signifie Local Area Network, c'est-à-dire un réseau local couvrant une zone géographique restreinte.
A15: 12 | B15: Facile | C15: Quelle adresse IPv4 est réservée au bouclage local (loopback) ? | D15: 192.168.0.1 | E15: 10.0.0.1 | F15: 255.255.255.255 | G15: 127.0.0.1 | H15: D | I15: L'adresse 127.0.0.1 est l'adresse de bouclage utilisée pour désigner la machine locale elle-même.
... A48: 45 | B48: Difficile | C48: Quel protocole de routage extérieur est utilisé pour l'échange de routes entre systèmes autonomes sur Internet ? | D48: OSPF | E48: EIGRP | F48: BGP | G48: RIP | H48: C | I48: BGP (Border Gateway Protocol) est le protocole de routage inter-domaines qui échange les routes entre systèmes autonomes.

Sheet Bases de données
A1: QCM — Bases de données
A2: 45 questions · 15 faciles · 15 moyennes · 15 difficiles — la bonne réponse est indiquée avec une explication.
A3: N° | B3: Difficulté | C3: Question | D3: Choix A | E3: Choix B | F3: Choix C | G3: Choix D | H3: Bonne réponse | I3: Explication
A4: 1 | B4: Facile | C4: Dans le modele relationnel, comment appelle-t-on une ligne d'une table ? | D4: Un tuple (ou enregistrement) | E4: Un attribut | F4: Un domaine | G4: Une relation | H4: A | I4: Une ligne d'une table correspond a un tuple, aussi appele enregistrement. La table elle-meme est la relation.
A5: 2 | B5: Facile | C5: Qu'est-ce qu'une cle primaire ? | D5: Un attribut qui peut contenir plusieurs valeurs NULL | E5: Un attribut qui identifie de maniere unique chaque ligne d'une table | F5: Un attribut toujours de type entier | G5: Un lien vers une autre table | H5: B | I5: La cle primaire identifie de facon unique chaque tuple d'une relation ; elle ne peut pas etre NULL.
A6: 3 | B6: Facile | C6: A quoi sert une cle etrangere ? | D6: A trier les donnees | E6: A chiffrer une colonne | F6: A referencer la cle primaire d'une autre table pour etablir un lien | G6: A accelerer les recherches uniquement | H6: C | I6: Une cle etrangere fait reference a la cle primaire (ou une cle candidate) d'une autre table afin de garantir l'integrite referentielle.
A7: 4 | B7: Facile | C7: Dans le modele entite-association, qu'est-ce qu'une entite ? | D7: Un index physique | E7: Une contrainte de domaine | F7: Une operation SQL | G7: Un objet ou concept du monde reel que l'on souhaite representer | H7: D | I7: Une entite represente un objet ou concept du monde reel (client, produit, commande) possedant des proprietes.
A8: 5 | B8: Facile | C8: Que signifie le sigle ACID en gestion de transactions ? | D8: Acces, Controle, Index, Donnees | E8: Atomicite, Coherence, Isolation, Durabilite | F8: Ajout, Copie, Insertion, Duplication | G8: Attribut, Cle, Instance, Domaine | H8: B | I8: ACID designe les quatre proprietes d'une transaction fiable : Atomicite, Coherence (Consistency), Isolation et Durabilite.
A9: 6 | B9: Facile | C9: Une base de donnees est dite relationnelle car elle organise les donnees sous forme de : | D9: Fichiers plats | E9: Arbres binaires uniquement | F9: Tables (relations) liees entre elles | G9: Documents JSON exclusivement | H9: C | I9: Le modele relationnel organise les donnees en tables (relations) reliees par des cles.
A10: 7 | B10: Facile | C10: Qu'appelle-t-on cardinalite dans un modele entite-association ? | D10: Le nombre de colonnes d'une table | E10: Le nombre d'index d'une table | F10: La taille en octets d'un enregistrement | G10: Le nombre minimal et maximal d'occurrences d'une entite participant a une association | H10: D | I10: La cardinalite exprime le nombre minimal et maximal de fois qu'une occurrence d'entite peut participer a une association.
A11: 8 | B11: Facile | C11: Une cle primaire peut-elle contenir une valeur NULL ? | D11: Non, jamais | E11: Oui, toujours | F11: Oui, seulement pour la premiere ligne | G11: Oui, si la table est vide | H11: A | I11: La contrainte d'entite impose qu'aucun attribut de la cle primaire ne soit NULL.
A12: 9 | B12: Facile | C12: Qu'est-ce qu'un index dans une base de donnees ? | D12: Une copie de sauvegarde de la table | E12: Une contrainte d'unicite obligatoire | F12: Une structure de donnees qui accelere la recherche des lignes | G12: Un type de donnees | H12: C | I12: Un index est une structure (souvent un arbre B) qui accelere l'acces aux lignes selon certaines colonnes.
A13: 10 | B13: Facile | C13: Dans une relation, un attribut represente : | D13: Une ligne | E13: Une transaction | F13: Une contrainte | G13: Une colonne (propriete) | H13: D | I13: Un attribut correspond a une colonne, c'est-a-dire une propriete des tuples de la relation.
A14: 11 | B14: Facile | C14: Qu'est-ce que l'integrite referentielle ? | D14: L'obligation qu'une cle etrangere pointe vers une valeur existante (ou soit NULL) | E14: L'unicite de toutes les colonnes | F14: Le chiffrement des cles primaires | G14: La suppression automatique des doublons | H14: A | I14: L'integrite referentielle garantit qu'une cle etrangere reference une valeur existante dans la table cible, ou vaut NULL.
A15: 12 | B15: Facile | C15: Une association de type plusieurs-a-plusieurs (N:M) se traduit en modele relationnel par : | D15: Une seule cle primaire composee dans une des tables | E15: Une table d'association (ou de jointure) supplementaire | F15: La fusion des deux tables | G15: Une vue | H15: B | I15: Une association N:M donne une table d'association dont la cle est generalement composee des cles etrangeres des deux entites.
... A48: 45 | B48: Difficile | C48: Le principe d'un verrou partage (shared lock, mode S) est : | D48: Il est pose uniquement au COMMIT | E48: Il bloque toute autre transaction, meme en lecture | F48: Il ne concerne que la cle primaire | G48: Il autorise plusieurs lectures simultanees mais bloque les ecritures | H48: D | I48: Un verrou partage (S) permet a plusieurs transactions de lire simultanement la ressource mais empeche toute ecriture (verrou exclusif) concurrente.

Sheet SQL
A1: QCM — SQL
A2: 45 questions · 15 faciles · 15 moyennes · 15 difficiles — la bonne réponse est indiquée avec une explication.
A3: N° | B3: Difficulté | C3: Question | D3: Choix A | E3: Choix B | F3: Choix C | G3: Choix D | H3: Bonne réponse | I3: Explication
A4: 1 | B4: Facile | C4: Quelle clause SQL permet de selectionner des colonnes dans une table ? | D4: SELECT | E4: INSERT | F4: UPDATE | G4: CREATE | H4: A | I4: SELECT est l'instruction de base pour extraire des colonnes et des lignes d'une ou plusieurs tables.
A5: 2 | B5: Facile | C5: Quelle clause filtre les lignes selon une condition ? | D5: ORDER BY | E5: WHERE | F5: GROUP BY | G5: HAVING | H5: B | I5: WHERE filtre les lignes avant tout regroupement, selon une condition portant sur les colonnes.
A6: 3 | B6: Facile | C6: Quelle requete recupere toutes les colonnes de la table Client ? | D6: GET * FROM Client; | E6: SELECT ALL Client; | F6: SELECT * FROM Client; | G6: SELECT Client.*; | H6: C | I6: SELECT * FROM Client; renvoie toutes les colonnes et toutes les lignes de la table Client.
A7: 4 | B7: Facile | C7: Quelle instruction ajoute une nouvelle ligne dans une table ? | D7: ADD ROW | E7: CREATE ROW | F7: APPEND | G7: INSERT INTO | H7: D | I7: INSERT INTO ajoute une ou plusieurs lignes dans une table.
A8: 5 | B8: Facile | C8: Quelle clause trie le resultat d'une requete ? | D8: SORT | E8: ORDER BY | F8: GROUP BY | G8: RANK | H8: B | I8: ORDER BY trie les lignes du resultat selon une ou plusieurs colonnes, en ASC (defaut) ou DESC.
A9: 6 | B9: Facile | C9: Quelle fonction d'agregation compte le nombre de lignes ? | D9: SUM() | E9: AVG() | F9: COUNT() | G9: MAX() | H9: C | I9: COUNT() renvoie le nombre de lignes ; COUNT(*) compte toutes les lignes, COUNT(col) ignore les NULL de col.
A10: 7 | B10: Facile | C10: Quelle instruction supprime des lignes d'une table sans supprimer la table ? | D10: DROP | E10: TRUNCATE COLUMN | F10: REMOVE | G10: DELETE | H10: D | I10: DELETE supprime des lignes (avec une clause WHERE optionnelle) tout en conservant la structure de la table.
A11: 8 | B11: Facile | C11: Quelle instruction modifie les valeurs de lignes existantes ? | D11: UPDATE | E11: ALTER | F11: MODIFY | G11: CHANGE | H11: A | I11: UPDATE modifie les valeurs de colonnes de lignes existantes, generalement avec une clause WHERE.
A12: 9 | B12: Facile | C12: Quelle instruction cree une nouvelle table ? | D12: MAKE TABLE | E12: NEW TABLE | F12: CREATE TABLE | G12: BUILD TABLE | H12: C | I12: CREATE TABLE definit une nouvelle table avec ses colonnes, types et contraintes.
A13: 10 | B13: Facile | C13: Que fait la clause DISTINCT dans SELECT DISTINCT ville FROM Client; ? | D13: Elle trie les villes | E13: Elle supprime les lignes NULL | F13: Elle compte les villes | G13: Elle elimine les doublons du resultat | H13: D | I13: DISTINCT elimine les lignes en double dans le resultat, ne conservant que les valeurs distinctes.
A14: 11 | B14: Facile | C14: Quel operateur teste l'appartenance a une liste de valeurs ? | D14: IN | E14: BETWEEN | F14: LIKE | G14: IS | H14: A | I14: IN teste si une valeur appartient a une liste, ex. WHERE ville IN ('Paris','Lyon').
A15: 12 | B15: Facile | C15: Quel operateur permet une recherche par motif sur du texte ? | D15: IN | E15: LIKE | F15: BETWEEN | G15: EXISTS | H15: B | I15: LIKE permet la recherche par motif avec les jokers % (n'importe quelle chaine) et _ (un caractere).
... A48: 45 | B48: Difficile | C48: Pourquoi WHERE prix > (SELECT AVG(prix) FROM Produit) est-elle valide alors que WHERE prix > AVG(prix) ne l'est pas ? | D48: WHERE n'accepte pas de comparaison numerique | E48: Les deux sont equivalentes | F48: La sous-requete est interdite | G48: AVG ne peut pas s'utiliser directement dans WHERE car WHERE agit avant l'agregation ; la sous-requete calcule d'abord la moyenne | H48: D | I48: WHERE est evaluee avant l'agregation, donc AVG() n'y est pas autorise directement ; la sous-requete calcule la moyenne separement, ce qui rend la comparaison valide.

Sheet Systèmes exploitation
A1: QCM — Systèmes d'exploitation
A2: 45 questions · 15 faciles · 15 moyennes · 15 difficiles — la bonne réponse est indiquée avec une explication.
A3: N° | B3: Difficulté | C3: Question | D3: Choix A | E3: Choix B | F3: Choix C | G3: Choix D | H3: Bonne réponse | I3: Explication
A4: 1 | B4: Facile | C4: Qu'est-ce qu'un processus dans un système d'exploitation ? | D4: Un programme en cours d'exécution | E4: Un fichier stocké sur le disque | F4: Un périphérique matériel | G4: Une adresse mémoire physique | H4: A | I4: Un processus est une instance d'un programme en cours d'exécution, avec son propre espace d'adressage et ses ressources.
A5: 2 | B5: Facile | C5: Quelle commande Linux affiche le contenu d'un répertoire ? | D5: cd | E5: ls | F5: pwd | G5: rm | H5: B | I5: La commande ls (list) affiche la liste des fichiers et répertoires du répertoire courant.
A6: 3 | B6: Facile | C6: Quel composant du système d'exploitation gère l'accès direct au matériel ? | D6: Le shell | E6: Le compilateur | F6: Le noyau (kernel) | G6: L'éditeur de texte | H6: C | I6: Le noyau est le cœur du système d'exploitation ; il gère le matériel, la mémoire et les processus.
A7: 4 | B7: Facile | C7: Qu'est-ce qu'un thread (fil d'exécution) ? | D7: Un processus indépendant avec son propre espace mémoire | E7: Un fichier temporaire | F7: Un type de système de fichiers | G7: Une unité d'exécution au sein d'un processus | H7: D | I7: Un thread est une unité d'exécution s'exécutant au sein d'un processus et partageant son espace d'adressage.
A8: 5 | B8: Facile | C8: Quelle commande Linux permet de changer de répertoire courant ? | D8: cd | E8: ls | F8: mv | G8: cp | H8: A | I8: La commande cd (change directory) permet de se déplacer dans l'arborescence des répertoires.
A9: 6 | B9: Facile | C9: Quel mécanisme permet à un programme utilisateur de demander un service au noyau ? | D9: Une interruption matérielle | E9: Un appel système | F9: Une variable d'environnement | G9: Un pointeur de pile | H9: B | I9: Un appel système (system call) est l'interface par laquelle un programme demande un service au noyau.
A10: 7 | B10: Facile | C10: Qu'est-ce que la mémoire vive (RAM) ? | D10: Une mémoire permanente | E10: Un disque dur | F10: Une mémoire volatile de travail | G10: Une mémoire cache du processeur uniquement | H10: C | I10: La RAM est une mémoire volatile qui stocke temporairement les données et programmes en cours d'exécution.
A11: 8 | B11: Facile | C11: Quelle commande Linux affiche le chemin du répertoire de travail courant ? | D11: whoami | E11: ls | F11: echo | G11: pwd | H11: D | I11: La commande pwd (print working directory) affiche le chemin absolu du répertoire courant.
A12: 9 | B12: Facile | C12: Qu'est-ce qu'un interblocage (deadlock) ? | D12: Un blocage mutuel où des processus s'attendent indéfiniment | E12: Un processus qui consomme tout le CPU | F12: Une erreur de compilation | G12: Une saturation du disque dur | H12: A | I12: Un interblocage survient lorsque des processus s'attendent mutuellement pour des ressources, sans qu'aucun ne puisse progresser.
A13: 10 | B13: Facile | C13: Quelle commande Linux permet de créer un nouveau répertoire ? | D13: touch | E13: mkdir | F13: rmdir | G13: cat | H13: B | I13: La commande mkdir (make directory) crée un nouveau répertoire.
A14: 11 | B14: Facile | C14: Qu'est-ce que l'ordonnancement (scheduling) des processus ? | D14: L'allocation de mémoire aux fichiers | E14: La compression des données | F14: La décision de quel processus s'exécute sur le processeur | G14: Le chiffrement des fichiers | H14: C | I14: L'ordonnancement décide quel processus prêt obtient le processeur et pendant combien de temps.
A15: 12 | B15: Facile | C15: Quelle commande Linux affiche les processus en cours d'exécution ? | D15: ls | E15: df | F15: du | G15: ps | H15: D | I15: La commande ps (process status) affiche les processus en cours d'exécution.
... A48: 45 | B48: Difficile | C48: Quel est l'intérêt principal d'une opération d'entrée/sortie par DMA (Direct Memory Access) ? | D48: Elle chiffre les données transférées | E48: Elle augmente la fréquence du processeur | F48: Elle permet le transfert de données sans intervention constante du processeur | G48: Elle supprime le besoin de mémoire vive | H48: C | I48: Le DMA permet à un périphérique de transférer des données directement vers la mémoire sans solliciter le processeur pour chaque octet, le libérant pour d'autres tâches.

Sheet Numération
A1: QCM — Numération
A2: 45 questions · 15 faciles · 15 moyennes · 15 difficiles — la bonne réponse est indiquée avec une explication.
A3: N° | B3: Difficulté | C3: Question | D3: Choix A | E3: Choix B | F3: Choix C | G3: Choix D | H3: Bonne réponse | I3: Explication
A4: 1 | B4: Facile | C4: Combien de symboles (chiffres) utilise le système binaire ? | D4: 2 | E4: 8 | F4: 10 | G4: 16 | H4: A | I4: Le système binaire n'utilise que deux symboles : 0 et 1.
A5: 2 | B5: Facile | C5: Quelle est la base du système hexadécimal ? | D5: 8 | E5: 16 | F5: 10 | G5: 2 | H5: B | I5: Le système hexadécimal est en base 16 et utilise les symboles 0 à 9 puis A à F.
A6: 3 | B6: Facile | C6: Quel est l'équivalent décimal du nombre binaire 1010 ? | D6: 8 | E6: 12 | F6: 10 | G6: 5 | H6: C | I6: 1010 en binaire vaut 1×8 + 0×4 + 1×2 + 0×1 = 8 + 2 = 10 en décimal.
A7: 4 | B7: Facile | C7: Combien de bits contient un octet ? | D7: 4 bits | E7: 16 bits | F7: 32 bits | G7: 8 bits | H7: D | I7: Par définition, un octet est composé de 8 bits.
A8: 5 | B8: Facile | C8: Quelle est la base du système octal ? | D8: 8 | E8: 16 | F8: 2 | G8: 10 | H8: A | I8: Le système octal est en base 8 et utilise les chiffres de 0 à 7.
A9: 6 | B9: Facile | C9: Quel est le plus grand chiffre utilisable en base 8 (octal) ? | D9: 8 | E9: 7 | F9: 9 | G9: F | H9: B | I9: En octal, les chiffres vont de 0 à 7 ; le chiffre 8 n'existe pas dans cette base.
A10: 7 | B10: Facile | C10: En hexadécimal, quelle valeur décimale représente la lettre A ? | D10: 11 | E10: 15 | F10: 10 | G10: 1 | H10: C | I10: En hexadécimal, A vaut 10, B vaut 11, ... et F vaut 15.
A11: 8 | B11: Facile | C11: Quel est l'équivalent binaire du nombre décimal 4 ? | D11: 110 | E11: 101 | F11: 010 | G11: 100 | H11: D | I11: 4 = 1×4 + 0×2 + 0×1, ce qui s'écrit 100 en binaire.
A12: 9 | B12: Facile | C12: Le code ASCII standard (original) code chaque caractère sur combien de bits ? | D12: 7 bits | E12: 8 bits | F12: 16 bits | G12: 4 bits | H12: A | I12: L'ASCII standard code 128 caractères sur 7 bits ; l'ASCII étendu utilise 8 bits pour 256 caractères.
A13: 10 | B13: Facile | C13: Combien de valeurs différentes peut représenter un ensemble de 8 bits ? | D13: 128 | E13: 256 | F13: 255 | G13: 512 | H13: B | I13: Avec 8 bits, on peut représenter 2^8 = 256 valeurs différentes (de 0 à 255).
A14: 11 | B14: Facile | C14: Quel est le bit de poids fort (MSB) du nombre binaire 1000 ? | D14: Le 0 le plus à droite | E14: Il n'y en a pas | F14: Le 1 le plus à gauche | G14: Le deuxième chiffre | H14: C | I14: Le bit de poids fort (Most Significant Bit) est le chiffre le plus à gauche, ici le 1, qui a la plus grande valeur (8).
A15: 12 | B15: Facile | C15: Quelle est la valeur décimale du nombre binaire 111 ? | D15: 5 | E15: 6 | F15: 8 | G15: 7 | H15: D | I15: 111 en binaire vaut 4 + 2 + 1 = 7 en décimal.
... A48: 45 | B48: Difficile | C48: En IEEE 754, les nombres dénormalisés (subnormaux) servent à : | D48: Représenter des valeurs très proches de zéro, plus petites que le plus petit normalisé | E48: Représenter l'infini | F48: Coder les entiers | G48: Accélérer les divisions | H48: A | I48: Les nombres dénormalisés (exposant tout à zéro, mantisse non nulle) permettent de représenter des valeurs plus petites que le plus petit nombre normalisé, assurant un dépassement progressif vers zéro.

Sheet PHP
A1: QCM — PHP
A2: 45 questions · 15 faciles · 15 moyennes · 15 difficiles — la bonne réponse est indiquée avec une explication.
A3: N° | B3: Difficulté | C3: Question | D3: Choix A | E3: Choix B | F3: Choix C | G3: Choix D | H3: Bonne réponse | I3: Explication
A4: 1 | B4: Facile | C4: Quelle balise ouvre un bloc de code PHP ? | D4: <?php | E4: <php> | F4: <script php> | G4: {php} | H4: A | I4: Un bloc PHP standard commence par <?php et se termine par ?>.
A5: 2 | B5: Facile | C5: Comment déclare-t-on une variable en PHP ? | D5: var nom = 'Ali'; | E5: $nom = 'Ali'; | F5: nom := 'Ali'; | G5: let nom = 'Ali'; | H5: B | I5: En PHP, toute variable est préfixée par le symbole $, par exemple $nom.
A6: 3 | B6: Facile | C6: Quel caractère termine une instruction en PHP ? | D6: Le point . | E6: La virgule , | F6: Le point-virgule ; | G6: Les deux-points : | H6: C | I6: Chaque instruction PHP se termine par un point-virgule ;.
A7: 4 | B7: Facile | C7: Quelle fonction affiche du texte à l'écran en PHP ? | D7: print_r() uniquement | E7: write() | F7: console.log() | G7: echo | H7: D | I7: echo est la construction la plus courante pour afficher une ou plusieurs chaînes.
A8: 5 | B8: Facile | C8: Comment écrit-on un commentaire sur une seule ligne en PHP ? | D8: # commentaire ou // commentaire | E8: <!-- commentaire --> | F8: ** commentaire | G8: ; commentaire | H8: A | I8: PHP accepte // et # pour les commentaires sur une ligne, et /* */ sur plusieurs lignes.
A9: 6 | B9: Facile | C9: Quel opérateur concatène deux chaînes en PHP ? | D9: + | E9: . | F9: & | G9: || | H9: B | I9: L'opérateur de concaténation en PHP est le point (.), contrairement au + du JavaScript.
A10: 7 | B10: Facile | C10: Comment crée-t-on un tableau indexé en PHP moderne ? | D10: $t = array{1, 2, 3}; | E10: $t = (1, 2, 3); | F10: $t = [1, 2, 3]; | G10: $t = new Array(1, 2, 3); | H10: C | I10: Depuis PHP 5.4, la syntaxe courte [] crée un tableau ; array(1, 2, 3) reste équivalent.
A11: 8 | B11: Facile | C11: Quelle superglobale contient les données envoyées par un formulaire en méthode POST ? | D11: $_GET | E11: $_FORM | F11: $_REQUEST uniquement | G11: $_POST | H11: D | I11: $_POST contient les données transmises via la méthode HTTP POST.
A12: 9 | B12: Facile | C12: Quelle fonction retourne le nombre d'éléments d'un tableau ? | D12: count() | E12: length() | F12: size() | G12: total() | H12: A | I12: count() renvoie le nombre d'éléments d'un tableau en PHP.
A13: 10 | B13: Facile | C13: Comment démarre-t-on une session en PHP ? | D13: start_session(); | E13: session_start(); | F13: session_begin(); | G13: $_SESSION->start(); | H13: B | I13: session_start() doit être appelée avant toute sortie pour initialiser ou reprendre une session.
A14: 11 | B14: Facile | C14: Quel mot-clé définit une fonction en PHP ? | D14: func | E14: def | F14: function | G14: fn uniquement | H14: C | I14: function déclare une fonction. fn existe aussi mais seulement pour les fonctions fléchées (arrow functions).
A15: 12 | B15: Facile | C15: Quelle est la valeur booléenne de la chaîne vide '' en contexte booléen ? | D15: true | E15: 1 | F15: null | G15: false | H15: D | I15: La chaîne vide '' est évaluée à false, tout comme '0', 0, null et le tableau vide.
... A48: 45 | B48: Difficile | C48: Que renvoie l'expression (int) '12abc' en PHP ? | D48: 12 | E48: 0 | F48: false | G48: Une erreur fatale | H48: A | I48: La conversion en entier lit les chiffres initiaux jusqu'au premier caractère non numérique : '12abc' donne 12 (un avertissement peut être émis).

Sheet POO concepts
A1: QCM — POO — concepts généraux
A2: 45 questions · 15 faciles · 15 moyennes · 15 difficiles — la bonne réponse est indiquée avec une explication.
A3: N° | B3: Difficulté | C3: Question | D3: Choix A | E3: Choix B | F3: Choix C | G3: Choix D | H3: Bonne réponse | I3: Explication
A4: 1 | B4: Facile | C4: Qu'est-ce qu'une classe en programmation orientée objet ? | D4: Une instance concrète stockée en mémoire | E4: Une fonction globale sans état | F4: Un modèle (patron) décrivant les attributs et méthodes d'objets | G4: Une variable de type primitif | H4: C | I4: Une classe est un modèle abstrait qui définit les attributs et comportements ; les objets en sont les instances concrètes.
A5: 2 | B5: Facile | C5: Qu'est-ce qu'un objet ? | D5: Le nom d'un fichier source | E5: Une instance concrète d'une classe | F5: Un mot-clé réservé du langage | G5: Un type de boucle | H5: B | I5: Un objet est une instance concrète créée à partir d'une classe, possédant un état propre.
A6: 3 | B6: Facile | C6: Que désigne l'encapsulation ? | D6: Le regroupement des données et des méthodes, en masquant les détails internes | E6: La duplication du code entre classes | F6: La création automatique d'objets | G6: La conversion de types | H6: A | I6: L'encapsulation regroupe état et comportement dans une même unité et restreint l'accès direct aux données internes.
A7: 4 | B7: Facile | C7: À quoi sert l'héritage ? | D7: À supprimer des objets de la mémoire | E7: À rendre toutes les méthodes privées | F7: À permettre à une classe de réutiliser et étendre une autre classe | G7: À interdire la création d'instances | H7: C | I7: L'héritage permet à une sous-classe de reprendre les membres d'une super-classe et de les étendre ou spécialiser.
A8: 5 | B8: Facile | C8: Qu'est-ce qu'un attribut (ou champ) d'une classe ? | D8: Une variable représentant une donnée de l'objet | E8: Le constructeur de la classe | F8: Un commentaire de documentation | G8: Une instruction de retour | H8: A | I8: Un attribut est une variable membre qui décrit une caractéristique de l'état d'un objet.
A9: 6 | B9: Facile | C9: Qu'est-ce qu'une méthode ? | D9: Un comportement (fonction) associé à une classe ou un objet | E9: Une donnée constante | F9: Un fichier de configuration | G9: Un type de collection | H9: A | I9: Une méthode définit un comportement de l'objet ; elle agit généralement sur l'état de celui-ci.
A10: 7 | B10: Facile | C10: Que représente le polymorphisme ? | D10: L'impossibilité de redéfinir une méthode | E10: La suppression des classes abstraites | F10: La capacité à traiter des objets de types différents via une interface commune | G10: L'allocation dynamique de mémoire | H10: C | I10: Le polymorphisme permet d'utiliser des objets de classes différentes de manière uniforme au travers d'un type commun.
A11: 8 | B11: Facile | C11: Qu'est-ce que l'abstraction en POO ? | D11: Le fait de tout rendre public | E11: La copie physique d'un objet | F11: Le fait de ne montrer que l'essentiel en masquant la complexité interne | G11: La compilation du code source | H11: C | I11: L'abstraction consiste à exposer un ensemble de fonctionnalités essentielles en cachant les détails de mise en oeuvre.
A12: 9 | B12: Facile | C12: Qu'est-ce qu'un constructeur ? | D12: Une interface | E12: Une méthode qui détruit l'objet | F12: Un attribut statique | G12: Une méthode spéciale servant à initialiser un objet | H12: D | I12: Le constructeur est appelé à la création de l'objet pour initialiser son état.
A13: 10 | B13: Facile | C13: Qu'est-ce qu'une interface au sens POO ? | D13: Un objet déjà instancié | E13: Une classe totalement concrète | F13: Un attribut privé | G13: Un contrat définissant des méthodes à implémenter, sans code métier | H13: D | I13: Une interface décrit un ensemble d'opérations qu'une classe s'engage à fournir, sans en imposer l'implémentation.
A14: 11 | B14: Facile | C14: Que signifie 'instancier' une classe ? | D14: Créer un objet à partir de cette classe | E14: La supprimer du programme | F14: La rendre abstraite | G14: La documenter | H14: A | I14: Instancier consiste à créer un objet concret, en réservant la mémoire et en initialisant son état.
A15: 12 | B15: Facile | C15: Quel principe consiste à cacher les attributs et à y accéder par des méthodes ? | D15: L'héritage | E15: L'encapsulation | F15: Le polymorphisme | G15: La récursivité | H15: B | I15: Contrôler l'accès aux attributs via des accesseurs (getters/setters) est une application de l'encapsulation.
... A48: 45 | B48: Difficile | C48: Que désigne la notion d'identité d'un objet ? | D48: La valeur de ses attributs uniquement | E48: Le fait qu'un objet reste distinct des autres même si ses attributs sont égaux | F48: Le nom de sa classe | G48: Sa visibilité (public/privé) | H48: B | I48: Deux objets peuvent avoir le même état (égalité) tout en étant des entités distinctes (identité différente).

Sheet C++
A1: QCM — C++
A2: 45 questions · 15 faciles · 15 moyennes · 15 difficiles — la bonne réponse est indiquée avec une explication.
A3: N° | B3: Difficulté | C3: Question | D3: Choix A | E3: Choix B | F3: Choix C | G3: Choix D | H3: Bonne réponse | I3: Explication
A4: 1 | B4: Facile | C4: Quel mot-clé permet d'allouer dynamiquement de la mémoire pour un objet en C++ ? | D4: malloc | E4: create | F4: alloc | G4: new | H4: D | I4: En C++, l'opérateur 'new' alloue de la mémoire dynamique et appelle le constructeur de l'objet.
A5: 2 | B5: Facile | C5: Quel opérateur libère la mémoire allouée par 'new' pour un objet simple ? | D5: free | E5: remove | F5: release | G5: delete | H5: D | I5: 'delete' libère la mémoire d'un objet alloué par 'new' et appelle son destructeur ; 'delete[]' est utilisé pour les tableaux.
A6: 3 | B6: Facile | C6: Comment déclare-t-on une référence vers un entier 'x' en C++ ? | D6: int &ref = x; | E6: int *ref = x; | F6: ref int = x; | G6: int ref = &x; | H6: A | I6: Une référence se déclare avec '&' et doit être initialisée immédiatement ; elle devient un alias de la variable.
A7: 4 | B7: Facile | C7: Quel en-tête faut-il inclure pour utiliser std::vector ? | D7: #include <vector> | E7: #include <array> | F7: #include <list> | G7: #include <stdlib.h> | H7: A | I7: Le conteneur std::vector est déclaré dans l'en-tête standard <vector>.
A8: 5 | B8: Facile | C8: Que fait l'instruction 'std::cout << x;' ? | D8: Elle écrit la valeur de x sur la sortie standard | E8: Elle lit x depuis l'entrée standard | F8: Elle supprime x | G8: Elle alloue de la mémoire pour x | H8: A | I8: std::cout est le flux de sortie standard ; l'opérateur << insère la valeur dans ce flux.
A9: 6 | B9: Facile | C9: Comment se nomme la méthode spéciale appelée à la destruction d'un objet ? | D9: Le constructeur | E9: L'accesseur | F9: Le destructeur | G9: Le mutateur | H9: C | I9: Le destructeur, noté '~NomClasse()', est appelé automatiquement lorsque l'objet est détruit pour libérer ses ressources.
A10: 7 | B10: Facile | C10: Quelle est la syntaxe correcte d'un destructeur pour une classe nommée 'A' ? | D10: void ~A(); | E10: ~A(); | F10: destroy A(); | G10: delete A(); | H10: B | I10: Le destructeur porte le nom de la classe précédé de '~', sans type de retour ni paramètre.
A11: 8 | B11: Facile | C11: Quel mot-clé rend une variable non modifiable après initialisation ? | D11: static | E11: final | F11: const | G11: readonly | H11: C | I11: 'const' indique que la valeur ne peut plus être modifiée après son initialisation.
A12: 9 | B12: Facile | C12: Comment ajoute-t-on un élément à la fin d'un std::vector nommé 'v' ? | D12: v.add(x); | E12: v.append(x); | F12: v.push_back(x); | G12: v.insert(x); | H12: C | I12: La méthode push_back ajoute un élément en fin de vecteur, en agrandissant sa capacité si nécessaire.
A13: 10 | B13: Facile | C13: Quel conteneur associatif de la STL stocke des paires clé-valeur triées par clé ? | D13: std::vector | E13: std::stack | F13: std::map | G13: std::array | H13: C | I13: std::map est un conteneur associatif ordonné qui associe des clés uniques à des valeurs, trié par clé.
A14: 11 | B14: Facile | C14: Que renvoie la méthode size() d'un std::vector ? | D14: Le nombre d'éléments contenus | E14: L'adresse du premier élément | F14: La capacité maximale possible | G14: La somme des éléments | H14: A | I14: size() retourne le nombre d'éléments actuellement stockés dans le vecteur.
A15: 12 | B15: Facile | C15: Comment accède-t-on à un membre 'm' via un pointeur 'p' vers un objet ? | D15: p.m | E15: *p.m | F15: p::m | G15: p->m | H15: D | I15: L'opérateur flèche '->' déréférence le pointeur et accède au membre ; il équivaut à (*p).m.
... A48: 45 | B48: Difficile | C48: Quelle est la différence entre std::vector::at(i) et l'opérateur [] ? | D48: at() ne vérifie pas les bornes, [] les vérifie | E48: at() vérifie les bornes et lève std::out_of_range, [] ne les vérifie pas | F48: Les deux lèvent toujours une exception | G48: Ils sont strictement équivalents | H48: B | I48: at() effectue une vérification des bornes et lève std::out_of_range en cas de dépassement, contrairement à l'opérateur [] non vérifié.

Sheet POO Java
A1: QCM — POO Java
A2: 45 questions · 15 faciles · 15 moyennes · 15 difficiles — la bonne réponse est indiquée avec une explication.
A3: N° | B3: Difficulté | C3: Question | D3: Choix A | E3: Choix B | F3: Choix C | G3: Choix D | H3: Bonne réponse | I3: Explication
A4: 1 | B4: Facile | C4: Quel mot-clé Java permet à une classe d'hériter d'une autre classe ? | D4: extends | E4: implements | F4: inherits | G4: super | H4: A | I4: En Java, 'extends' établit l'héritage entre une sous-classe et sa super-classe.
A5: 2 | B5: Facile | C5: Quel mot-clé une classe utilise-t-elle pour fournir une interface ? | D5: extends | E5: uses | F5: implements | G5: import | H5: C | I5: Une classe utilise 'implements' pour indiquer qu'elle réalise une ou plusieurs interfaces.
A6: 3 | B6: Facile | C6: Quel modificateur d'accès rend un membre visible uniquement dans sa propre classe ? | D6: private | E6: public | F6: protected | G6: default | H6: A | I6: 'private' restreint l'accès au membre à l'intérieur de la classe où il est déclaré.
A7: 4 | B7: Facile | C7: Comment crée-t-on une instance de la classe 'Voiture' en Java ? | D7: Voiture v = create Voiture; | E7: Voiture v = Voiture(); | F7: new v = Voiture; | G7: Voiture v = new Voiture(); | H7: D | I7: L'opérateur 'new' suivi d'un appel au constructeur crée un nouvel objet et retourne sa référence.
A8: 5 | B8: Facile | C8: Quel mot-clé désigne l'objet courant à l'intérieur d'une méthode d'instance ? | D8: self | E8: me | F8: this | G8: current | H8: C | I8: 'this' fait référence à l'instance courante sur laquelle la méthode est appelée.
A9: 6 | B9: Facile | C9: Quelle est la classe racine de toutes les classes en Java ? | D9: Main | E9: System | F9: Object | G9: Base | H9: C | I9: Toute classe Java hérite implicitement de java.lang.Object, racine de la hiérarchie.
A10: 7 | B10: Facile | C10: Quel mot-clé empêche la redéfinition d'une méthode dans les sous-classes ? | D10: static | E10: sealed | F10: const | G10: final | H10: D | I10: Une méthode déclarée 'final' ne peut pas être redéfinie par une classe dérivée.
A11: 8 | B11: Facile | C11: Comment déclare-t-on une constante de classe en Java ? | D11: static final int MAX = 10; | E11: const int MAX = 10; | F11: final static readonly int MAX = 10; | G11: immutable int MAX = 10; | H11: A | I11: Une constante s'exprime par 'static final' : partagée par la classe et non modifiable.
A12: 9 | B12: Facile | C12: Quel mot-clé permet d'appeler le constructeur de la super-classe ? | D12: this() | E12: super() | F12: parent() | G12: base() | H12: B | I12: 'super()' invoque le constructeur de la super-classe ; il doit être la première instruction du constructeur.
A13: 10 | B13: Facile | C13: Quelle interface de collection représente une liste ordonnée autorisant les doublons ? | D13: List | E13: Set | F13: Map | G13: Queue | H13: A | I13: L'interface List (ex. ArrayList) conserve l'ordre d'insertion et autorise les éléments dupliqués.
A14: 11 | B14: Facile | C14: Quelle implémentation de Map la plus courante stocke des paires clé-valeur sans ordre garanti ? | D14: TreeMap | E14: HashMap | F14: ArrayList | G14: HashSet | H14: B | I14: HashMap stocke des associations clé-valeur via une table de hachage, sans garantie d'ordre.
A15: 12 | B15: Facile | C15: Quel bloc permet de capturer une exception en Java ? | D15: if / else | E15: try / catch | F15: switch / case | G15: do / while | H15: B | I15: Le bloc 'try' contient le code susceptible d'échouer, et 'catch' intercepte l'exception levée.
... A48: 45 | B48: Difficile | C48: Qu'est-ce qu'une interface fonctionnelle en Java 8 ? | D48: Une classe abstraite particulière | E48: Une interface sans aucune méthode | F48: Une interface comportant exactement une méthode abstraite, utilisable avec une expression lambda | G48: Une interface qui ne peut pas être implémentée | H48: C | I48: Une interface fonctionnelle possède une seule méthode abstraite (SAM) et peut être fournie sous forme de lambda ou de référence de méthode.

Sheet UML
A1: QCM — UML
A2: 45 questions · 15 faciles · 15 moyennes · 15 difficiles — la bonne réponse est indiquée avec une explication.
A3: N° | B3: Difficulté | C3: Question | D3: Choix A | E3: Choix B | F3: Choix C | G3: Choix D | H3: Bonne réponse | I3: Explication
A4: 1 | B4: Facile | C4: Que signifie le sigle UML ? | D4: Unified Modeling Language | E4: Universal Model Language | F4: Unified Method Logic | G4: User Modeling Layer | H4: A | I4: UML signifie Unified Modeling Language, un langage de modelisation standardise par l'OMG.
A5: 2 | B5: Facile | C5: Quel diagramme UML represente les classes et leurs relations ? | D5: Diagramme de cas d'utilisation | E5: Diagramme de classes | F5: Diagramme de sequence | G5: Diagramme d'activite | H5: B | I5: Le diagramme de classes decrit la structure statique : classes, attributs, methodes et relations entre elles.
A6: 3 | B6: Facile | C6: Quel diagramme UML decrit les interactions entre l'utilisateur (acteur) et le systeme du point de vue fonctionnel ? | D6: Diagramme d'etat-transition | E6: Diagramme de classes | F6: Diagramme de cas d'utilisation | G6: Diagramme de deploiement | H6: C | I6: Le diagramme de cas d'utilisation (use case) modelise les fonctionnalites offertes aux acteurs.
A7: 4 | B7: Facile | C7: Dans un diagramme de classes, une classe est generalement representee par un rectangle divise en : | D7: Deux parties : nom et methodes | E7: Quatre parties | F7: Une seule partie | G7: Trois parties : nom, attributs, methodes (operations) | H7: D | I7: Une classe se represente par un rectangle a trois compartiments : nom, attributs, puis operations (methodes).
A8: 5 | B8: Facile | C8: Qu'est-ce qu'un acteur dans un diagramme de cas d'utilisation ? | D8: Une classe interne | E8: Une entite externe (personne ou systeme) qui interagit avec le systeme | F8: Un attribut | G8: Une base de donnees | H8: B | I8: Un acteur represente un role externe (utilisateur, autre systeme) interagissant avec le systeme etudie.
A9: 6 | B9: Facile | C9: Quel diagramme UML montre l'ordre chronologique des messages echanges entre objets ? | D9: Diagramme de classes | E9: Diagramme de composants | F9: Diagramme de sequence | G9: Diagramme de cas d'utilisation | H9: C | I9: Le diagramme de sequence represente les interactions entre objets ordonnees dans le temps le long de lignes de vie.
A10: 7 | B10: Facile | C10: Quel diagramme UML represente un flux d'activites et de decisions, proche d'un organigramme ? | D10: Diagramme d'objets | E10: Diagramme de classes | F10: Diagramme de deploiement | G10: Diagramme d'activite | H10: D | I10: Le diagramme d'activite modelise un enchainement d'actions, de decisions et de flux, a la maniere d'un organigramme.
A11: 8 | B11: Facile | C11: Que modelise un diagramme d'etat-transition ? | D11: Les differents etats d'un objet et les transitions entre eux | E11: La structure des classes | F11: Le materiel physique | G11: Les acteurs du systeme | H11: A | I11: Le diagramme d'etat-transition (machine a etats) decrit les etats successifs d'un objet et les evenements provoquant les transitions.
A12: 9 | B12: Facile | C12: Dans un diagramme de classes, l'heritage (generalisation) se represente par : | D12: Une simple ligne pointillee | E12: Un losange plein | F12: Une fleche en trait plein avec un triangle vide pointant vers la classe mere | G12: Un cercle | H12: C | I12: La generalisation/heritage est notee par une fleche a triangle vide (non rempli) dirigee de la sous-classe vers la super-classe.
A13: 10 | B13: Facile | C13: Que represente une multiplicite '1..*' sur une association ? | D13: Zero ou une occurrence | E13: Exactement une occurrence | F13: Aucune occurrence | G13: Une ou plusieurs occurrences (au moins une) | H13: D | I13: La multiplicite 1..* signifie 'au moins un', soit une ou plusieurs occurrences.
A14: 11 | B14: Facile | C14: Quel diagramme UML represente la disposition physique du materiel (serveurs, noeuds) ? | D14: Diagramme de deploiement | E14: Diagramme de sequence | F14: Diagramme d'activite | G14: Diagramme de classes | H14: A | I14: Le diagramme de deploiement montre les noeuds materiels (serveurs, dispositifs) et la repartition des artefacts logiciels.
A15: 12 | B15: Facile | C15: Dans un diagramme de classes, une methode (operation) represente : | D15: Une donnee stockee | E15: Un comportement/une action que la classe peut executer | F15: Une relation entre classes | G15: Un acteur | H15: B | I15: Une operation (methode) decrit un comportement que les instances de la classe peuvent realiser.
... A48: 45 | B48: Difficile | C48: Un noeud initial dans un diagramme d'activite se represente par : | D48: Une barre horizontale | E48: Un cercle plein entoure d'un anneau | F48: Un losange | G48: Un cercle plein (rond noir) | H48: D | I48: Le noeud initial est un disque plein (rond noir) ; le noeud de fin d'activite est un rond noir cercle (cible), a ne pas confondre.

Sheet Développement web
A1: QCM — Développement web
A2: 45 questions · 15 faciles · 15 moyennes · 15 difficiles — la bonne réponse est indiquée avec une explication.
A3: N° | B3: Difficulté | C3: Question | D3: Choix A | E3: Choix B | F3: Choix C | G3: Choix D | H3: Bonne réponse | I3: Explication
A4: 1 | B4: Facile | C4: Quelle balise HTML5 sémantique désigne le contenu principal et unique d'une page ? | D4: <main> | E4: <div> | F4: <section> | G4: <content> | H4: A | I4: <main> représente le contenu central de la page ; il ne doit apparaître qu'une seule fois.
A5: 2 | B5: Facile | C5: Quel attribut HTML rend obligatoire la saisie d'un champ de formulaire ? | D5: mandatory | E5: required | F5: needed | G5: validate | H5: B | I5: L'attribut booléen required empêche l'envoi du formulaire si le champ est vide.
A6: 3 | B6: Facile | C6: Quelle propriété CSS change la couleur du texte ? | D6: font-color | E6: text-color | F6: color | G6: foreground | H6: C | I6: La propriété color définit la couleur du texte d'un élément.
A7: 4 | B7: Facile | C7: Quel sélecteur CSS cible un élément par son identifiant id='menu' ? | D7: .menu | E7: *menu | F7: menu | G7: #menu | H7: D | I7: Le dièse # cible un id, tandis que le point . cible une classe.
A8: 5 | B8: Facile | C8: Quelle valeur de la propriété display active un conteneur flexbox ? | D8: display: flex; | E8: display: block; | F8: display: flexbox; | G8: display: grid; | H8: A | I8: display: flex; transforme un élément en conteneur flexible dont les enfants deviennent des items flex.
A9: 6 | B9: Facile | C9: Quelle méthode JavaScript sélectionne un élément par son id ? | D9: document.querySelectorAll('#id') | E9: document.getElementById('id') | F9: document.getElement('id') | G9: document.findId('id') | H9: B | I9: getElementById() renvoie l'élément unique correspondant à l'identifiant fourni, ou null s'il n'existe pas.
A10: 7 | B10: Facile | C10: Quelle méthode HTTP est utilisée pour récupérer une ressource sans la modifier ? | D10: POST | E10: PUT | F10: GET | G10: DELETE | H10: C | I10: GET demande une ressource sans effet de bord ; elle est idempotente et sûre.
A11: 8 | B11: Facile | C11: Que signifie le code de statut HTTP 404 ? | D11: Requête réussie | E11: Accès interdit | F11: Erreur interne du serveur | G11: Ressource non trouvée | H11: D | I11: 404 Not Found indique que le serveur n'a pas trouvé la ressource demandée.
A12: 9 | B12: Facile | C12: Quelle balise HTML crée un lien hypertexte ? | D12: <a> | E12: <link> | F12: <href> | G12: <url> | H12: A | I12: La balise <a> avec l'attribut href crée un lien ; <link> sert à référencer des ressources externes dans <head>.
A13: 10 | B13: Facile | C13: Quel framework CSS utilise un système de grille basé sur 12 colonnes et des classes comme col-md-6 ? | D13: Tailwind | E13: Bootstrap | F13: Foundation | G13: Bulma | H13: B | I13: Bootstrap propose une grille responsive à 12 colonnes avec des classes telles que col-md-6.
A14: 11 | B14: Facile | C14: Quelle balise <meta> est indispensable au responsive design pour adapter la largeur à l'écran ? | D14: <meta charset='utf-8'> | E14: <meta name='responsive' content='true'> | F14: <meta name='viewport' content='width=device-width, initial-scale=1'> | G14: <meta http-equiv='refresh'> | H14: C | I14: La meta viewport indique au navigateur d'adapter la largeur de la page à celle de l'appareil.
A15: 12 | B15: Facile | C15: Quelle API du navigateur stocke des données persistantes côté client sans date d'expiration ? | D15: sessionStorage | E15: cacheStorage | F15: cookieStorage | G15: localStorage | H15: D | I15: localStorage conserve les données même après la fermeture du navigateur, contrairement à sessionStorage limité à la session.
... A48: 45 | B48: Difficile | C48: En CSS, que produit box-sizing: border-box sur un élément ? | D48: La largeur définie inclut le contenu, le padding et la bordure | E48: La largeur définie exclut le padding et la bordure | F48: Elle supprime toute bordure | G48: Elle transforme l'élément en flex | H48: A | I48: Avec border-box, la propriété width englobe le contenu, le padding et la bordure, ce qui simplifie le calcul des dimensions.
